elasticsearchmappinggenerator/elasticsearchmappinggenerator.py
elasticsearchmappinggenerator-2.0.0.dist-info/LICENSE
elasticsearchmappinggenerator-2.0.0.dist-info/METADATA
elasticsearchmappinggenerator-2.0.0.dist-info/WHEEL
elasticsearchmappinggenerator-2.0.0.dist-info/top_level.txt
elasticsearchmappinggenerator-2.0.0.dist-info/RECORD
