Metadata-Version: 2.1
Name: elasticsearchmappinggenerator
Version: 2.0.0
Summary: 
Home-page: https://github.com/soumilshah1995/elasticsearch-mapping-generator
Author: Soumil Nitin Shah
Author-email: soushah@my.bridgeport.edu
License: MIT
Platform: UNKNOWN
Classifier: License :: OSI Approved :: MIT License
Classifier: Programming Language :: Python :: 3
Classifier: Programming Language :: Python :: 3.7
